<?xml version="1.0" ?><list><model.Member><firstName>Ben</firstName><lastName>Stiller</lastName><accountName>Ben</accountName><passWord>pass</passWord><ratedFilms><entry><model.Film><id>62</id><title>Big Hero 6 </title><year>1993</year><genre>Action</genre><ratings><model.Rating>REALLY_LIKED_IT</model.Rating></ratings><totalRatingValue>5</totalRatingValue><numOfViewers>1</numOfViewers></model.Film><model.Rating>REALLY_LIKED_IT</model.Rating></entry><entry><model.Film><id>65</id><title>Fury</title><year>2003</year><genre>Comedy</genre><ratings><model.Rating>REALLY_LIKED_IT</model.Rating></ratings><totalRatingValue>5</totalRatingValue><numOfViewers>1</numOfViewers></model.Film><model.Rating>REALLY_LIKED_IT</model.Rating></entry><entry><model.Film><id>47</id><title>A Few Good Men</title><year>1992</year><genre>Crime</genre><ratings><model.Rating>REALLY_LIKED_IT</model.Rating></ratings><totalRatingValue>5</totalRatingValue><numOfViewers>1</numOfViewers></model.Film><model.Rating>REALLY_LIKED_IT</model.Rating></entry><entry><model.Film><id>1</id><title>Stick It</title><year>2006</year><genre>Comedy</genre><ratings><model.Rating>REALLY_LIKED_IT</model.Rating></ratings><totalRatingValue>5</totalRatingValue><numOfViewers>1</numOfViewers></model.Film><model.Rating>REALLY_LIKED_IT</model.Rating></entry><entry><model.Film><id>34</id><title>Ong-bak</title><year>2003</year><genre>Action</genre><ratings><model.Rating>TERRIBLE</model.Rating></ratings><totalRatingValue>-5</totalRatingValue><numOfViewers>1</numOfViewers></model.Film><model.Rating>TERRIBLE</model.Rating></entry><entry><model.Film><id>74</id><title>Maleficent</title><year>2014</year><genre>Fantasy</genre><ratings><model.Rating>REALLY_LIKED_IT</model.Rating><model.Rating>REALLY_LIKED_IT</model.Rating><model.Rating>REALLY_LIKED_IT</model.Rating><model.Rating>REALLY_LIKED_IT</model.Rating><model.Rating>REALLY_LIKED_IT</model.Rating></ratings><totalRatingValue>25</totalRatingValue><numOfViewers>5</numOfViewers></model.Film><model.Rating>REALLY_LIKED_IT</model.Rating></entry><entry><model.Film><id>2</id><title>Batman</title><year>1993</year><genre>Action</genre><ratings><model.Rating>LIKED_IT</model.Rating><model.Rating>LIKED_IT</model.Rating></ratings><totalRatingValue>6</totalRatingValue><numOfViewers>2</numOfViewers></model.Film><model.Rating>LIKED_IT</model.Rating></entry><entry><model.Film><id>33</id><title>Unfaithful</title><year>2002</year><genre>Drama</genre><ratings><model.Rating>LIKED_IT</model.Rating></ratings><totalRatingValue>3</totalRatingValue><numOfViewers>1</numOfViewers></model.Film><model.Rating>LIKED_IT</model.Rating></entry></ratedFilms><myFilms><model.Film reference="../../ratedFilms/entry[3]/model.Film"></model.Film><model.Film reference="../../ratedFilms/entry/model.Film"></model.Film><model.Film reference="../../ratedFilms/entry[7]/model.Film"></model.Film><model.Film reference="../../ratedFilms/entry[8]/model.Film"></model.Film><model.Film reference="../../ratedFilms/entry[5]/model.Film"></model.Film><model.Film reference="../../ratedFilms/entry[2]/model.Film"></model.Film><model.Film reference="../../ratedFilms/entry[4]/model.Film"></model.Film><model.Film reference="../../ratedFilms/entry[6]/model.Film"></model.Film></myFilms></model.Member><model.Member><firstName>John</firstName><lastName>Moose</lastName><accountName>Moose</accountName><passWord>pass</passWord><ratedFilms></ratedFilms><myFilms></myFilms></model.Member><model.Member><firstName>Reuven</firstName><lastName>Power</lastName><accountName>Reuven</accountName><passWord>pass</passWord><ratedFilms></ratedFilms><myFilms></myFilms></model.Member><model.Member><firstName>Mick</firstName><lastName>Thorhill</lastName><accountName>Cust1</accountName><passWord>pass</passWord><ratedFilms></ratedFilms><myFilms></myFilms></model.Member><model.Member><firstName>John</firstName><lastName>Palmer</lastName><accountName>Cust2</accountName><passWord>pass</passWord><ratedFilms></ratedFilms><myFilms></myFilms></model.Member><model.Member><firstName>Frank</firstName><lastName>Power</lastName><accountName>Francois</accountName><passWord>pass</passWord><ratedFilms></ratedFilms><myFilms></myFilms></model.Member><model.Member><firstName>Jim</firstName><lastName>Power</lastName><accountName>Jim</accountName><passWord>pass</passWord><ratedFilms></ratedFilms><myFilms></myFilms></model.Member><model.Member><firstName>Irene</firstName><lastName>Baker</lastName><accountName>Iren</accountName><passWord>pass</passWord><ratedFilms></ratedFilms><myFilms></myFilms></model.Member><model.Member><firstName>Abdul</firstName><lastName>OConnor</lastName><accountName>Cust3</accountName><passWord>pass</passWord><ratedFilms></ratedFilms><myFilms></myFilms></model.Member><model.Member><firstName>Kevin</firstName><lastName>Dean</lastName><accountName>Cust4</accountName><passWord>pass</passWord><ratedFilms></ratedFilms><myFilms></myFilms></model.Member><model.Member><firstName>Henry</firstName><lastName>Shefflin</lastName><accountName>Cust5</accountName><passWord>pass</passWord><ratedFilms></ratedFilms><myFilms></myFilms></model.Member><model.Member><firstName>Tom</firstName><lastName>Power</lastName><accountName>Cust6</accountName><passWord>pass</passWord><ratedFilms></ratedFilms><myFilms></myFilms></model.Member><model.Member><firstName>Peter</firstName><lastName>North</lastName><accountName>Cust7</accountName><passWord>pass</passWord><ratedFilms></ratedFilms><myFilms></myFilms></model.Member><model.Member><firstName>Bob</firstName><lastName>Dylan</lastName><accountName>Cust8</accountName><passWord>pass</passWord><ratedFilms></ratedFilms><myFilms></myFilms></model.Member><model.Member><firstName>Bob</firstName><lastName>Hoskins</lastName><accountName>Cust9</accountName><passWord>pass</passWord><ratedFilms></ratedFilms><myFilms></myFilms></model.Member><model.Member><firstName>Andrew</firstName><lastName>Smores</lastName><accountName>andrew</accountName><passWord>pass</passWord><ratedFilms></ratedFilms><myFilms></myFilms></model.Member><model.Member><firstName>Mary</firstName><lastName>Everet</lastName><accountName>ma</accountName><passWord>pass</passWord><ratedFilms></ratedFilms><myFilms></myFilms></model.Member><model.Member><firstName>Mat</firstName><lastName>Corner</lastName><accountName>matt</accountName><passWord>pass</passWord><ratedFilms></ratedFilms><myFilms></myFilms></model.Member><model.Member><firstName>Mat</firstName><lastName>Baker</lastName><accountName>Ocelot</accountName><passWord>pass</passWord><ratedFilms></ratedFilms><myFilms></myFilms></model.Member><model.Member><firstName>Jean</firstName><lastName>Walsh</lastName><accountName>Cust10</accountName><passWord>pass</passWord><ratedFilms></ratedFilms><myFilms></myFilms></model.Member><model.Member><firstName>Paddy</firstName><lastName>Walsh</lastName><accountName>crom</accountName><passWord>pass</passWord><ratedFilms></ratedFilms><myFilms></myFilms></model.Member><model.Member><firstName>Joe</firstName><lastName>Whelan</lastName><accountName>joe</accountName><passWord>pass</passWord><ratedFilms></ratedFilms><myFilms></myFilms></model.Member><model.Member><firstName>Priscilla</firstName><lastName>Desert</lastName><accountName>Priscilla</accountName><passWord>pass</passWord><ratedFilms></ratedFilms><myFilms></myFilms></model.Member><model.Member><firstName>Harry</firstName><lastName>Potter</lastName><accountName>Harry</accountName><passWord>pass</passWord><ratedFilms></ratedFilms><myFilms></myFilms></model.Member><model.Member><firstName>Ned</firstName><lastName>Kelly</lastName><accountName>Ned</accountName><passWord>pass</passWord><ratedFilms></ratedFilms><myFilms></myFilms></model.Member><model.Member><firstName>Harry</firstName><lastName>Potter</lastName><accountName>ender</accountName><passWord>pass</passWord><ratedFilms></ratedFilms><myFilms></myFilms></model.Member><model.Member><firstName>Harry</firstName><lastName>Potter</lastName><accountName>Apollo</accountName><passWord>pass</passWord><ratedFilms></ratedFilms><myFilms></myFilms></model.Member><model.Member><firstName>Harry</firstName><lastName>Potter</lastName><accountName>Zax</accountName><passWord>pass</passWord><ratedFilms></ratedFilms><myFilms></myFilms></model.Member><model.Member><firstName>Harry</firstName><lastName>Potter</lastName><accountName>Jaluka</accountName><passWord>pass</passWord><ratedFilms></ratedFilms><myFilms></myFilms></model.Member><model.Member><firstName>Harry</firstName><lastName>Potter</lastName><accountName>Sanity</accountName><passWord>pass</passWord><ratedFilms></ratedFilms><myFilms></myFilms></model.Member><model.Member><firstName>Harry</firstName><lastName>Potter</lastName><accountName>Brix</accountName><passWord>pass</passWord><ratedFilms></ratedFilms><myFilms></myFilms></model.Member><model.Member><firstName>Harry</firstName><lastName>Potter</lastName><accountName>sage32</accountName><passWord>pass</passWord><ratedFilms></ratedFilms><myFilms></myFilms></model.Member><model.Member><firstName>Harry</firstName><lastName>Potter</lastName><accountName>clipper</accountName><passWord>pass</passWord><ratedFilms><entry><model.Film><id>1</id><title>Stick It</title><year>2006</year><genre>Comedy</genre><ratings><model.Rating>REALLY_LIKED_IT</model.Rating><model.Rating>LIKED_IT</model.Rating><model.Rating>REALLY_LIKED_IT</model.Rating><model.Rating>REALLY_LIKED_IT</model.Rating><model.Rating>TERRIBLE</model.Rating><model.Rating>TERRIBLE</model.Rating><model.Rating>LIKED_IT</model.Rating><model.Rating>REALLY_LIKED_IT</model.Rating><model.Rating>TERRIBLE</model.Rating><model.Rating>REALLY_LIKED_IT</model.Rating><model.Rating>TERRIBLE</model.Rating><model.Rating>OK</model.Rating></ratings><totalRatingValue>12</totalRatingValue><numOfViewers>12</numOfViewers></model.Film><model.Rating>OK</model.Rating></entry><entry><model.Film><id>35</id><title>The Lookout</title><year>2007</year><genre>Crime</genre><ratings><model.Rating>REALLY_LIKED_IT</model.Rating><model.Rating>REALLY_LIKED_IT</model.Rating><model.Rating>REALLY_LIKED_IT</model.Rating><model.Rating>REALLY_LIKED_IT</model.Rating></ratings><totalRatingValue>20</totalRatingValue><numOfViewers>4</numOfViewers></model.Film><model.Rating>REALLY_LIKED_IT</model.Rating></entry><entry><model.Film><id>2</id><title>Batman</title><year>1993</year><genre>Action</genre><ratings><model.Rating>LIKED_IT</model.Rating><model.Rating>LIKED_IT</model.Rating><model.Rating>TERRIBLE</model.Rating><model.Rating>TERRIBLE</model.Rating><model.Rating>LIKED_IT</model.Rating><model.Rating>LIKED_IT</model.Rating><model.Rating>TERRIBLE</model.Rating><model.Rating>TERRIBLE</model.Rating><model.Rating>LIKED_IT</model.Rating><model.Rating>LIKED_IT</model.Rating></ratings><totalRatingValue>-2</totalRatingValue><numOfViewers>10</numOfViewers></model.Film><model.Rating>LIKED_IT</model.Rating></entry></ratedFilms><myFilms><model.Film reference="../../ratedFilms/entry[3]/model.Film"></model.Film><model.Film reference="../../ratedFilms/entry/model.Film"></model.Film><model.Film reference="../../ratedFilms/entry[2]/model.Film"></model.Film></myFilms></model.Member><model.Member><firstName>Harry</firstName><lastName>Potter</lastName><accountName>YJAM</accountName><passWord>pass</passWord><ratedFilms></ratedFilms><myFilms></myFilms></model.Member><model.Member><firstName>Harry</firstName><lastName>Potter</lastName><accountName>Martin</accountName><passWord>pass</passWord><ratedFilms></ratedFilms><myFilms></myFilms></model.Member><model.Member><firstName>Harry</firstName><lastName>Potter</lastName><accountName>Mike</accountName><passWord>pass</passWord><ratedFilms></ratedFilms><myFilms></myFilms></model.Member><model.Member><firstName>Harry</firstName><lastName>Potter</lastName><accountName>Strongbad</accountName><passWord>pass</passWord><ratedFilms></ratedFilms><myFilms></myFilms></model.Member><model.Member><firstName>Harry</firstName><lastName>Potter</lastName><accountName>Brian</accountName><passWord>pass</passWord><ratedFilms></ratedFilms><myFilms></myFilms></model.Member><model.Member><firstName>Douglas</firstName><lastName>Anderson</lastName><accountName>Douglas</accountName><passWord>pass</passWord><ratedFilms></ratedFilms><myFilms></myFilms></model.Member><model.Member><firstName>Chris</firstName><lastName>Green</lastName><accountName>chrispeh</accountName><passWord>pass</passWord><ratedFilms></ratedFilms><myFilms></myFilms></model.Member><model.Member><firstName>Rudy</firstName><lastName>Whirl</lastName><accountName>Rudy</accountName><passWord>pass</passWord><ratedFilms></ratedFilms><myFilms></myFilms></model.Member><model.Member><firstName>Tim</firstName><lastName>Black</lastName><accountName>McLovin</accountName><passWord>pass</passWord><ratedFilms></ratedFilms><myFilms></myFilms></model.Member><model.Member><firstName>Mike</firstName><lastName>Williams</lastName><accountName>Mike</accountName><passWord>pass</passWord><ratedFilms></ratedFilms><myFilms></myFilms></model.Member><model.Member><firstName>Chris</firstName><lastName>Green</lastName><accountName>Dude</accountName><passWord>pass</passWord><ratedFilms></ratedFilms><myFilms></myFilms></model.Member><model.Member><firstName>Chris</firstName><lastName>Green</lastName><accountName>Hideo</accountName><passWord>pass</passWord><ratedFilms></ratedFilms><myFilms></myFilms></model.Member><model.Member><firstName>Rudy</firstName><lastName>Ann</lastName><accountName>Rudy</accountName><passWord>pass</passWord><ratedFilms></ratedFilms><myFilms></myFilms></model.Member><model.Member><firstName>Don</firstName><lastName>Wang</lastName><accountName>Don</accountName><passWord>pass</passWord><ratedFilms></ratedFilms><myFilms></myFilms></model.Member><model.Member><firstName>Anna</firstName><lastName>Carol</lastName><accountName>Anna</accountName><passWord>pass</passWord><ratedFilms></ratedFilms><myFilms></myFilms></model.Member><model.Member><firstName>Anna</firstName><lastName>Carol</lastName><accountName>SubRia</accountName><passWord>pass</passWord><ratedFilms></ratedFilms><myFilms></myFilms></model.Member><model.Member><firstName>Ella</firstName><lastName>Carol</lastName><accountName>Ella</accountName><passWord>pass</passWord><ratedFilms></ratedFilms><myFilms></myFilms></model.Member><model.Member><firstName>Leslie</firstName><lastName>Carol</lastName><accountName>Leslie</accountName><passWord>pass</passWord><ratedFilms></ratedFilms><myFilms></myFilms></model.Member><model.Member><firstName>Sam</firstName><lastName>Green</lastName><accountName>Sam</accountName><passWord>pass</passWord><ratedFilms></ratedFilms><myFilms></myFilms></model.Member><model.Member><firstName>Cederic</firstName><lastName>Jones</lastName><accountName>Cedric</accountName><passWord>pass</passWord><ratedFilms></ratedFilms><myFilms></myFilms></model.Member><model.Member><firstName>Dan</firstName><lastName>Wang</lastName><accountName>Don</accountName><passWord>pass</passWord><ratedFilms></ratedFilms><myFilms></myFilms></model.Member><model.Member><firstName>John</firstName><lastName>MClean</lastName><accountName>McLean</accountName><passWord>pass</passWord><ratedFilms></ratedFilms><myFilms></myFilms></model.Member><model.Member><firstName>Mary</firstName><lastName>Shannon</lastName><accountName>Shannon</accountName><passWord>pass</passWord><ratedFilms><entry><model.Film><id>23</id><title>Outlander</title><year>2008</year><genre>Action</genre><ratings><model.Rating>TERRIBLE</model.Rating><model.Rating>LIKED_IT</model.Rating><model.Rating>REALLY_LIKED_IT</model.Rating></ratings><totalRatingValue>3</totalRatingValue><numOfViewers>3</numOfViewers></model.Film><model.Rating>REALLY_LIKED_IT</model.Rating></entry><entry><model.Film><id>1</id><title>Stick It</title><year>2006</year><genre>Comedy</genre><ratings><model.Rating>REALLY_LIKED_IT</model.Rating><model.Rating>LIKED_IT</model.Rating><model.Rating>REALLY_LIKED_IT</model.Rating><model.Rating>REALLY_LIKED_IT</model.Rating><model.Rating>TERRIBLE</model.Rating><model.Rating>TERRIBLE</model.Rating><model.Rating>LIKED_IT</model.Rating><model.Rating>REALLY_LIKED_IT</model.Rating><model.Rating>TERRIBLE</model.Rating><model.Rating>REALLY_LIKED_IT</model.Rating></ratings><totalRatingValue>16</totalRatingValue><numOfViewers>10</numOfViewers></model.Film><model.Rating>REALLY_LIKED_IT</model.Rating></entry><entry><model.Film><id>36</id><title>War</title><year>2007</year><genre>Action</genre><ratings><model.Rating>TERRIBLE</model.Rating></ratings><totalRatingValue>-5</totalRatingValue><numOfViewers>1</numOfViewers></model.Film><model.Rating>TERRIBLE</model.Rating></entry><entry><model.Film><id>46</id><title>AVP: Alien vs. Predator</title><year>2004</year><genre>Action</genre><ratings><model.Rating>REALLY_LIKED_IT</model.Rating><model.Rating>TERRIBLE</model.Rating><model.Rating>REALLY_LIKED_IT</model.Rating><model.Rating>REALLY_LIKED_IT</model.Rating></ratings><totalRatingValue>10</totalRatingValue><numOfViewers>4</numOfViewers></model.Film><model.Rating>REALLY_LIKED_IT</model.Rating></entry><entry><model.Film><id>66</id><title>Guardians of the Galaxy</title><year>2005</year><genre>Crime</genre><ratings><model.Rating>REALLY_LIKED_IT</model.Rating><model.Rating>TERRIBLE</model.Rating><model.Rating>LIKED_IT</model.Rating><model.Rating>REALLY_LIKED_IT</model.Rating></ratings><totalRatingValue>8</totalRatingValue><numOfViewers>4</numOfViewers></model.Film><model.Rating>LIKED_IT</model.Rating></entry><entry><model.Film><id>28</id><title>Universal Soldier</title><year>1992</year><genre>Action</genre><ratings><model.Rating>TERRIBLE</model.Rating></ratings><totalRatingValue>-5</totalRatingValue><numOfViewers>1</numOfViewers></model.Film><model.Rating>TERRIBLE</model.Rating></entry></ratedFilms><myFilms><model.Film reference="../../ratedFilms/entry[6]/model.Film"></model.Film><model.Film reference="../../ratedFilms/entry[4]/model.Film"></model.Film><model.Film reference="../../ratedFilms/entry[5]/model.Film"></model.Film><model.Film reference="../../ratedFilms/entry[2]/model.Film"></model.Film><model.Film reference="../../ratedFilms/entry[3]/model.Film"></model.Film><model.Film reference="../../ratedFilms/entry/model.Film"></model.Film></myFilms></model.Member><model.Member><firstName>Joshua</firstName><lastName>Brown</lastName><accountName>Joshua</accountName><passWord>pass</passWord><ratedFilms></ratedFilms><myFilms></myFilms></model.Member><model.Member><firstName>Jeremy</firstName><lastName>White</lastName><accountName>Jeremy</accountName><passWord>pass</passWord><ratedFilms></ratedFilms><myFilms></myFilms></model.Member><model.Member><firstName>Pable</firstName><lastName>Sanchez</lastName><accountName>Pablo</accountName><passWord>pass</passWord><ratedFilms><entry><model.Film reference="../../../../model.Member[33]/ratedFilms/entry/model.Film"></model.Film><model.Rating>TERRIBLE</model.Rating></entry><entry><model.Film><id>3</id><title>Virtuosity</title><year>1995</year><genre>Action</genre><ratings><model.Rating>TERRIBLE</model.Rating><model.Rating>TERRIBLE</model.Rating><model.Rating>LIKED_IT</model.Rating></ratings><totalRatingValue>-7</totalRatingValue><numOfViewers>3</numOfViewers></model.Film><model.Rating>LIKED_IT</model.Rating></entry><entry><model.Film><id>5</id><title>Anything Else</title><year>2003</year><genre>Comedy</genre><ratings><model.Rating>TERRIBLE</model.Rating><model.Rating>REALLY_LIKED_IT</model.Rating><model.Rating>REALLY_LIKED_IT</model.Rating></ratings><totalRatingValue>5</totalRatingValue><numOfViewers>3</numOfViewers></model.Film><model.Rating>REALLY_LIKED_IT</model.Rating></entry><entry><model.Film reference="../../../../model.Member[56]/ratedFilms/entry[4]/model.Film"></model.Film><model.Rating>REALLY_LIKED_IT</model.Rating></entry><entry><model.Film reference="../../../../model.Member[56]/ratedFilms/entry[5]/model.Film"></model.Film><model.Rating>REALLY_LIKED_IT</model.Rating></entry><entry><model.Film><id>64</id><title>The Hunger Games: Mockingjay - Part 1</title><year>2001</year><genre>Action</genre><ratings><model.Rating>REALLY_LIKED_IT</model.Rating><model.Rating>REALLY_LIKED_IT</model.Rating><model.Rating>DIDNT_LIKE_IT</model.Rating><model.Rating>REALLY_LIKED_IT</model.Rating><model.Rating>REALLY_LIKED_IT</model.Rating></ratings><totalRatingValue>17</totalRatingValue><numOfViewers>5</numOfViewers></model.Film><model.Rating>REALLY_LIKED_IT</model.Rating></entry></ratedFilms><myFilms><model.Film reference="../../ratedFilms/entry[2]/model.Film"></model.Film><model.Film reference="../../ratedFilms/entry[6]/model.Film"></model.Film><model.Film reference="../../ratedFilms/entry[3]/model.Film"></model.Film><model.Film reference="../../../model.Member[56]/ratedFilms/entry[4]/model.Film"></model.Film><model.Film reference="../../../model.Member[56]/ratedFilms/entry[5]/model.Film"></model.Film><model.Film reference="../../../model.Member[33]/ratedFilms/entry/model.Film"></model.Film></myFilms></model.Member><model.Member><firstName>mary</firstName><lastName>Terry</lastName><accountName>Scream</accountName><passWord>pass</passWord><ratedFilms></ratedFilms><myFilms></myFilms></model.Member><model.Member><firstName>John</firstName><lastName>zappa</lastName><accountName>ROFLOL</accountName><passWord>pass</passWord><ratedFilms></ratedFilms><myFilms></myFilms></model.Member><model.Member><firstName>Albus</firstName><lastName>Dumbledore</lastName><accountName>Albus</accountName><passWord>pass</passWord><ratedFilms></ratedFilms><myFilms></myFilms></model.Member><model.Member><firstName>Alexandra</firstName><lastName>Dumbledore</lastName><accountName>Alexandra</accountName><passWord>pass</passWord><ratedFilms></ratedFilms><myFilms></myFilms></model.Member><model.Member><firstName>Clodagh</firstName><lastName>Reder</lastName><accountName>NaRwHaLs</accountName><passWord>pass</passWord><ratedFilms></ratedFilms><myFilms></myFilms></model.Member><model.Member><firstName>Jeremy</firstName><lastName>Kyle</lastName><accountName>J-Rok</accountName><passWord>pass</passWord><ratedFilms></ratedFilms><myFilms></myFilms></model.Member><model.Member><firstName>Jeremy</firstName><lastName>White</lastName><accountName>snoosh</accountName><passWord>pass</passWord><ratedFilms></ratedFilms><myFilms></myFilms></model.Member><model.Member><firstName>Jeremy</firstName><lastName>Blond</lastName><accountName>Huxil</accountName><passWord>pass</passWord><ratedFilms></ratedFilms><myFilms></myFilms></model.Member><model.Member><firstName>Jeremy</firstName><lastName>Topper</lastName><accountName>hidan</accountName><passWord>pass</passWord><ratedFilms></ratedFilms><myFilms></myFilms></model.Member><model.Member><firstName>Leah</firstName><lastName>White</lastName><accountName>Leah</accountName><passWord>pass</passWord><ratedFilms></ratedFilms><myFilms></myFilms></model.Member><model.Member><firstName>Bob</firstName><lastName>Blind</lastName><accountName>Boxxy</accountName><passWord>pass</passWord><ratedFilms></ratedFilms><myFilms></myFilms></model.Member><model.Member><firstName>Rosanna</firstName><lastName>King</lastName><accountName>Rosanna</accountName><passWord>pass</passWord><ratedFilms></ratedFilms><myFilms></myFilms></model.Member><model.Member><firstName>Claire</firstName><lastName>Rush</lastName><accountName>Claire</accountName><passWord>pass</passWord><ratedFilms><entry><model.Film><id>64</id><title>The Hunger Games: Mockingjay - Part 1</title><year>2001</year><genre>Action</genre><ratings><model.Rating>REALLY_LIKED_IT</model.Rating><model.Rating>REALLY_LIKED_IT</model.Rating><model.Rating>DIDNT_LIKE_IT</model.Rating></ratings><totalRatingValue>7</totalRatingValue><numOfViewers>3</numOfViewers></model.Film><model.Rating>DIDNT_LIKE_IT</model.Rating></entry><entry><model.Film><id>45</id><title>Jurassic Park III</title><year>2001</year><genre>Action</genre><ratings><model.Rating>DIDNT_LIKE_IT</model.Rating><model.Rating>TERRIBLE</model.Rating></ratings><totalRatingValue>-8</totalRatingValue><numOfViewers>2</numOfViewers></model.Film><model.Rating>TERRIBLE</model.Rating></entry><entry><model.Film><id>63</id><title>Dumb and Dumber To </title><year>1995</year><genre>Action</genre><ratings><model.Rating>REALLY_LIKED_IT</model.Rating></ratings><totalRatingValue>5</totalRatingValue><numOfViewers>1</numOfViewers></model.Film><model.Rating>REALLY_LIKED_IT</model.Rating></entry><entry><model.Film><id>2</id><title>Batman</title><year>1993</year><genre>Action</genre><ratings><model.Rating>LIKED_IT</model.Rating><model.Rating>LIKED_IT</model.Rating><model.Rating>TERRIBLE</model.Rating><model.Rating>TERRIBLE</model.Rating></ratings><totalRatingValue>-4</totalRatingValue><numOfViewers>4</numOfViewers></model.Film><model.Rating>TERRIBLE</model.Rating></entry><entry><model.Film><id>61</id><title>Interstellar </title><year>2006</year><genre>Comedy</genre><ratings><model.Rating>REALLY_LIKED_IT</model.Rating><model.Rating>REALLY_LIKED_IT</model.Rating></ratings><totalRatingValue>10</totalRatingValue><numOfViewers>2</numOfViewers></model.Film><model.Rating>REALLY_LIKED_IT</model.Rating></entry><entry><model.Film><id>62</id><title>Big Hero 6 </title><year>1993</year><genre>Action</genre><ratings><model.Rating>REALLY_LIKED_IT</model.Rating><model.Rating>LIKED_IT</model.Rating><model.Rating>OK</model.Rating><model.Rating>TERRIBLE</model.Rating></ratings><totalRatingValue>4</totalRatingValue><numOfViewers>4</numOfViewers></model.Film><model.Rating>TERRIBLE</model.Rating></entry><entry><model.Film><id>1</id><title>Stick It</title><year>2006</year><genre>Comedy</genre><ratings><model.Rating>REALLY_LIKED_IT</model.Rating><model.Rating>LIKED_IT</model.Rating><model.Rating>REALLY_LIKED_IT</model.Rating><model.Rating>REALLY_LIKED_IT</model.Rating></ratings><totalRatingValue>18</totalRatingValue><numOfViewers>4</numOfViewers></model.Film><model.Rating>REALLY_LIKED_IT</model.Rating></entry><entry><model.Film><id>74</id><title>Maleficent</title><year>2014</year><genre>Fantasy</genre><ratings><model.Rating>REALLY_LIKED_IT</model.Rating><model.Rating>REALLY_LIKED_IT</model.Rating></ratings><totalRatingValue>10</totalRatingValue><numOfViewers>2</numOfViewers></model.Film><model.Rating>REALLY_LIKED_IT</model.Rating></entry><entry><model.Film><id>35</id><title>The Lookout</title><year>2007</year><genre>Crime</genre><ratings><model.Rating>REALLY_LIKED_IT</model.Rating><model.Rating>REALLY_LIKED_IT</model.Rating></ratings><totalRatingValue>10</totalRatingValue><numOfViewers>2</numOfViewers></model.Film><model.Rating>REALLY_LIKED_IT</model.Rating></entry></ratedFilms><myFilms><model.Film reference="../../ratedFilms/entry[6]/model.Film"></model.Film><model.Film reference="../../ratedFilms/entry[4]/model.Film"></model.Film><model.Film reference="../../ratedFilms/entry[3]/model.Film"></model.Film><model.Film reference="../../ratedFilms/entry[2]/model.Film"></model.Film><model.Film reference="../../ratedFilms/entry/model.Film"></model.Film><model.Film reference="../../ratedFilms/entry[5]/model.Film"></model.Film><model.Film reference="../../ratedFilms/entry[7]/model.Film"></model.Film><model.Film reference="../../ratedFilms/entry[9]/model.Film"></model.Film><model.Film reference="../../ratedFilms/entry[8]/model.Film"></model.Film></myFilms></model.Member><model.Member><firstName>Dave</firstName><lastName>White</lastName><accountName>David</accountName><passWord>pass</passWord><ratedFilms></ratedFilms><myFilms></myFilms></model.Member><model.Member><firstName>Zachary</firstName><lastName>Rosanna</lastName><accountName>Zachary</accountName><passWord>pass</passWord><ratedFilms><entry><model.Film><id>2</id><title>Batman</title><year>1993</year><genre>Action</genre><ratings><model.Rating>LIKED_IT</model.Rating><model.Rating>LIKED_IT</model.Rating><model.Rating>TERRIBLE</model.Rating><model.Rating>TERRIBLE</model.Rating><model.Rating>LIKED_IT</model.Rating><model.Rating>LIKED_IT</model.Rating><model.Rating>TERRIBLE</model.Rating><model.Rating>TERRIBLE</model.Rating><model.Rating>LIKED_IT</model.Rating></ratings><totalRatingValue>-5</totalRatingValue><numOfViewers>9</numOfViewers></model.Film><model.Rating>TERRIBLE</model.Rating></entry><entry><model.Film><id>55</id><title>Star Trek</title><year>2009</year><genre>Action</genre><ratings><model.Rating>TERRIBLE</model.Rating><model.Rating>LIKED_IT</model.Rating></ratings><totalRatingValue>-2</totalRatingValue><numOfViewers>2</numOfViewers></model.Film><model.Rating>LIKED_IT</model.Rating></entry><entry><model.Film reference="../../../../model.Member[56]/ratedFilms/entry[2]/model.Film"></model.Film><model.Rating>LIKED_IT</model.Rating></entry><entry><model.Film><id>62</id><title>Big Hero 6 </title><year>1993</year><genre>Action</genre><ratings><model.Rating>REALLY_LIKED_IT</model.Rating><model.Rating>LIKED_IT</model.Rating><model.Rating>OK</model.Rating><model.Rating>TERRIBLE</model.Rating><model.Rating>TERRIBLE</model.Rating></ratings><totalRatingValue>-1</totalRatingValue><numOfViewers>5</numOfViewers></model.Film><model.Rating>TERRIBLE</model.Rating></entry><entry><model.Film><id>45</id><title>Jurassic Park III</title><year>2001</year><genre>Action</genre><ratings><model.Rating>DIDNT_LIKE_IT</model.Rating><model.Rating>TERRIBLE</model.Rating><model.Rating>TERRIBLE</model.Rating><model.Rating>LIKED_IT</model.Rating><model.Rating>TERRIBLE</model.Rating><model.Rating>REALLY_LIKED_IT</model.Rating></ratings><totalRatingValue>-10</totalRatingValue><numOfViewers>6</numOfViewers></model.Film><model.Rating>LIKED_IT</model.Rating></entry></ratedFilms><myFilms><model.Film reference="../../ratedFilms/entry[4]/model.Film"></model.Film><model.Film reference="../../ratedFilms/entry/model.Film"></model.Film><model.Film reference="../../ratedFilms/entry[5]/model.Film"></model.Film><model.Film reference="../../../model.Member[56]/ratedFilms/entry[2]/model.Film"></model.Film><model.Film reference="../../ratedFilms/entry[2]/model.Film"></model.Film></myFilms></model.Member><model.Member><firstName>Zachary</firstName><lastName>Neder</lastName><accountName>ParseClaws</accountName><passWord>pass</passWord><ratedFilms></ratedFilms><myFilms></myFilms></model.Member><model.Member><firstName>Tiffany</firstName><lastName>Zachary</lastName><accountName>Tiffany</accountName><passWord>pass</passWord><ratedFilms><entry><model.Film><id>74</id><title>Maleficent</title><year>2014</year><genre>Fantasy</genre><ratings><model.Rating>REALLY_LIKED_IT</model.Rating></ratings><totalRatingValue>5</totalRatingValue><numOfViewers>1</numOfViewers></model.Film><model.Rating>REALLY_LIKED_IT</model.Rating></entry><entry><model.Film><id>35</id><title>The Lookout</title><year>2007</year><genre>Crime</genre><ratings><model.Rating>REALLY_LIKED_IT</model.Rating></ratings><totalRatingValue>5</totalRatingValue><numOfViewers>1</numOfViewers></model.Film><model.Rating>REALLY_LIKED_IT</model.Rating></entry><entry><model.Film><id>1</id><title>Stick It</title><year>2006</year><genre>Comedy</genre><ratings><model.Rating>REALLY_LIKED_IT</model.Rating><model.Rating>LIKED_IT</model.Rating></ratings><totalRatingValue>8</totalRatingValue><numOfViewers>2</numOfViewers></model.Film><model.Rating>LIKED_IT</model.Rating></entry><entry><model.Film><id>62</id><title>Big Hero 6 </title><year>1993</year><genre>Action</genre><ratings><model.Rating>REALLY_LIKED_IT</model.Rating><model.Rating>LIKED_IT</model.Rating></ratings><totalRatingValue>8</totalRatingValue><numOfViewers>2</numOfViewers></model.Film><model.Rating>LIKED_IT</model.Rating></entry><entry><model.Film><id>65</id><title>Fury</title><year>2003</year><genre>Comedy</genre><ratings><model.Rating>REALLY_LIKED_IT</model.Rating><model.Rating>REALLY_LIKED_IT</model.Rating></ratings><totalRatingValue>10</totalRatingValue><numOfViewers>2</numOfViewers></model.Film><model.Rating>REALLY_LIKED_IT</model.Rating></entry><entry><model.Film><id>2</id><title>Batman</title><year>1993</year><genre>Action</genre><ratings><model.Rating>LIKED_IT</model.Rating><model.Rating>LIKED_IT</model.Rating><model.Rating>TERRIBLE</model.Rating></ratings><totalRatingValue>1</totalRatingValue><numOfViewers>3</numOfViewers></model.Film><model.Rating>TERRIBLE</model.Rating></entry><entry><model.Film><id>44</id><title>Once Upon a Time in Mexico</title><year>2003</year><genre>Action</genre><ratings><model.Rating>LIKED_IT</model.Rating></ratings><totalRatingValue>3</totalRatingValue><numOfViewers>1</numOfViewers></model.Film><model.Rating>LIKED_IT</model.Rating></entry></ratedFilms><myFilms><model.Film reference="../../ratedFilms/entry[6]/model.Film"></model.Film><model.Film reference="../../ratedFilms/entry[4]/model.Film"></model.Film><model.Film reference="../../ratedFilms/entry[7]/model.Film"></model.Film><model.Film reference="../../ratedFilms/entry[5]/model.Film"></model.Film><model.Film reference="../../ratedFilms/entry[3]/model.Film"></model.Film><model.Film reference="../../ratedFilms/entry[2]/model.Film"></model.Film><model.Film reference="../../ratedFilms/entry/model.Film"></model.Film></myFilms></model.Member><model.Member><firstName>Sidney</firstName><lastName>Jones</lastName><accountName>Sidney</accountName><passWord>pass</passWord><ratedFilms><entry><model.Film><id>33</id><title>Unfaithful</title><year>2002</year><genre>Drama</genre><ratings><model.Rating>LIKED_IT</model.Rating><model.Rating>TERRIBLE</model.Rating><model.Rating>LIKED_IT</model.Rating></ratings><totalRatingValue>1</totalRatingValue><numOfViewers>3</numOfViewers></model.Film><model.Rating>LIKED_IT</model.Rating></entry><entry><model.Film reference="../../../../model.Member[74]/ratedFilms/entry/model.Film"></model.Film><model.Rating>LIKED_IT</model.Rating></entry><entry><model.Film><id>46</id><title>AVP: Alien vs. Predator</title><year>2004</year><genre>Action</genre><ratings><model.Rating>REALLY_LIKED_IT</model.Rating><model.Rating>TERRIBLE</model.Rating></ratings><totalRatingValue>0</totalRatingValue><numOfViewers>2</numOfViewers></model.Film><model.Rating>TERRIBLE</model.Rating></entry><entry><model.Film reference="../../../../model.Member[56]/ratedFilms/entry[2]/model.Film"></model.Film><model.Rating>TERRIBLE</model.Rating></entry><entry><model.Film><id>3</id><title>Virtuosity</title><year>1995</year><genre>Action</genre><ratings><model.Rating>TERRIBLE</model.Rating><model.Rating>TERRIBLE</model.Rating></ratings><totalRatingValue>-10</totalRatingValue><numOfViewers>2</numOfViewers></model.Film><model.Rating>TERRIBLE</model.Rating></entry><entry><model.Film><id>66</id><title>Guardians of the Galaxy</title><year>2005</year><genre>Crime</genre><ratings><model.Rating>REALLY_LIKED_IT</model.Rating><model.Rating>TERRIBLE</model.Rating></ratings><totalRatingValue>0</totalRatingValue><numOfViewers>2</numOfViewers></model.Film><model.Rating>TERRIBLE</model.Rating></entry><entry><model.Film reference="../../../../model.Member[74]/ratedFilms/entry[5]/model.Film"></model.Film><model.Rating>TERRIBLE</model.Rating></entry></ratedFilms><myFilms><model.Film reference="../../../model.Member[74]/ratedFilms/entry/model.Film"></model.Film><model.Film reference="../../ratedFilms/entry[5]/model.Film"></model.Film><model.Film reference="../../../model.Member[74]/ratedFilms/entry[5]/model.Film"></model.Film><model.Film reference="../../ratedFilms/entry/model.Film"></model.Film><model.Film reference="../../ratedFilms/entry[3]/model.Film"></model.Film><model.Film reference="../../ratedFilms/entry[6]/model.Film"></model.Film><model.Film reference="../../../model.Member[56]/ratedFilms/entry[2]/model.Film"></model.Film></myFilms></model.Member><model.Member><firstName>Tony</firstName><lastName>Penkert</lastName><accountName>Tony</accountName><passWord>pass</passWord><ratedFilms></ratedFilms><myFilms></myFilms></model.Member><model.Member><firstName>Mark</firstName><lastName>Green</lastName><accountName>Mark</accountName><passWord>pass</passWord><ratedFilms><entry><model.Film reference="../../../../model.Member[74]/ratedFilms/entry/model.Film"></model.Film><model.Rating>LIKED_IT</model.Rating></entry><entry><model.Film reference="../../../../model.Member[56]/ratedFilms/entry[2]/model.Film"></model.Film><model.Rating>TERRIBLE</model.Rating></entry><entry><model.Film><id>74</id><title>Maleficent</title><year>2014</year><genre>Fantasy</genre><ratings><model.Rating>REALLY_LIKED_IT</model.Rating><model.Rating>REALLY_LIKED_IT</model.Rating><model.Rating>REALLY_LIKED_IT</model.Rating><model.Rating>REALLY_LIKED_IT</model.Rating></ratings><totalRatingValue>20</totalRatingValue><numOfViewers>4</numOfViewers></model.Film><model.Rating>REALLY_LIKED_IT</model.Rating></entry><entry><model.Film><id>7</id><title>Black Sheep</title><year>2006</year><genre></genre><ratings><model.Rating>TERRIBLE</model.Rating></ratings><totalRatingValue>-5</totalRatingValue><numOfViewers>1</numOfViewers></model.Film><model.Rating>TERRIBLE</model.Rating></entry><entry><model.Film><id>63</id><title>Dumb and Dumber To </title><year>1995</year><genre>Action</genre><ratings><model.Rating>REALLY_LIKED_IT</model.Rating><model.Rating>LIKED_IT</model.Rating></ratings><totalRatingValue>8</totalRatingValue><numOfViewers>2</numOfViewers></model.Film><model.Rating>LIKED_IT</model.Rating></entry><entry><model.Film><id>4</id><title>Alias</title><year>2001</year><genre>Action</genre><ratings><model.Rating>REALLY_LIKED_IT</model.Rating></ratings><totalRatingValue>5</totalRatingValue><numOfViewers>1</numOfViewers></model.Film><model.Rating>REALLY_LIKED_IT</model.Rating></entry></ratedFilms><myFilms><model.Film reference="../../../model.Member[74]/ratedFilms/entry/model.Film"></model.Film><model.Film reference="../../ratedFilms/entry[5]/model.Film"></model.Film><model.Film reference="../../ratedFilms/entry[6]/model.Film"></model.Film><model.Film reference="../../../model.Member[56]/ratedFilms/entry[2]/model.Film"></model.Film><model.Film reference="../../ratedFilms/entry[4]/model.Film"></model.Film><model.Film reference="../../ratedFilms/entry[3]/model.Film"></model.Film></myFilms></model.Member><model.Member><firstName>Jim</firstName><lastName>Bobel</lastName><accountName>NuNu</accountName><passWord>pass</passWord><ratedFilms></ratedFilms><myFilms></myFilms></model.Member><model.Member><firstName>Hamza</firstName><lastName>Ali</lastName><accountName>Hamza</accountName><passWord>pass</passWord><ratedFilms></ratedFilms><myFilms></myFilms></model.Member><model.Member><firstName>Diane</firstName><lastName>Bean</lastName><accountName>dencellia</accountName><passWord>pass</passWord><ratedFilms></ratedFilms><myFilms></myFilms></model.Member><model.Member><firstName>Nathen</firstName><lastName>green</lastName><accountName>Nathan</accountName><passWord>pass</passWord><ratedFilms></ratedFilms><myFilms></myFilms></model.Member><model.Member><firstName>James</firstName><lastName>Kepler</lastName><accountName>James</accountName><passWord>pass</passWord><ratedFilms><entry><model.Film reference="../../../../model.Member[74]/ratedFilms/entry/model.Film"></model.Film><model.Rating>TERRIBLE</model.Rating></entry><entry><model.Film><id>35</id><title>The Lookout</title><year>2007</year><genre>Crime</genre><ratings><model.Rating>REALLY_LIKED_IT</model.Rating><model.Rating>REALLY_LIKED_IT</model.Rating><model.Rating>REALLY_LIKED_IT</model.Rating></ratings><totalRatingValue>15</totalRatingValue><numOfViewers>3</numOfViewers></model.Film><model.Rating>REALLY_LIKED_IT</model.Rating></entry><entry><model.Film><id>5</id><title>Anything Else</title><year>2003</year><genre>Comedy</genre><ratings><model.Rating>TERRIBLE</model.Rating><model.Rating>REALLY_LIKED_IT</model.Rating></ratings><totalRatingValue>0</totalRatingValue><numOfViewers>2</numOfViewers></model.Film><model.Rating>REALLY_LIKED_IT</model.Rating></entry><entry><model.Film reference="../../../../model.Member[56]/ratedFilms/entry[2]/model.Film"></model.Film><model.Rating>REALLY_LIKED_IT</model.Rating></entry><entry><model.Film><id>64</id><title>The Hunger Games: Mockingjay - Part 1</title><year>2001</year><genre>Action</genre><ratings><model.Rating>REALLY_LIKED_IT</model.Rating><model.Rating>REALLY_LIKED_IT</model.Rating><model.Rating>DIDNT_LIKE_IT</model.Rating><model.Rating>REALLY_LIKED_IT</model.Rating></ratings><totalRatingValue>12</totalRatingValue><numOfViewers>4</numOfViewers></model.Film><model.Rating>REALLY_LIKED_IT</model.Rating></entry><entry><model.Film reference="../../../../model.Member[74]/ratedFilms/entry[5]/model.Film"></model.Film><model.Rating>TERRIBLE</model.Rating></entry></ratedFilms><myFilms><model.Film reference="../../../model.Member[74]/ratedFilms/entry/model.Film"></model.Film><model.Film reference="../../ratedFilms/entry[5]/model.Film"></model.Film><model.Film reference="../../../model.Member[74]/ratedFilms/entry[5]/model.Film"></model.Film><model.Film reference="../../ratedFilms/entry[3]/model.Film"></model.Film><model.Film reference="../../../model.Member[56]/ratedFilms/entry[2]/model.Film"></model.Film><model.Film reference="../../ratedFilms/entry[2]/model.Film"></model.Film></myFilms></model.Member><model.Member><firstName>Keeled</firstName><lastName>Goner</lastName><accountName>KeeLed</accountName><passWord>pass</passWord><ratedFilms><entry><model.Film><id>23</id><title>Outlander</title><year>2008</year><genre>Action</genre><ratings><model.Rating>TERRIBLE</model.Rating><model.Rating>LIKED_IT</model.Rating></ratings><totalRatingValue>-2</totalRatingValue><numOfViewers>2</numOfViewers></model.Film><model.Rating>LIKED_IT</model.Rating></entry><entry><model.Film><id>24</id><title>Empire Records</title><year>1995</year><genre>Comedy</genre><ratings><model.Rating>TERRIBLE</model.Rating></ratings><totalRatingValue>-5</totalRatingValue><numOfViewers>1</numOfViewers></model.Film><model.Rating>TERRIBLE</model.Rating></entry><entry><model.Film reference="../../../../model.Member[74]/ratedFilms/entry/model.Film"></model.Film><model.Rating>LIKED_IT</model.Rating></entry><entry><model.Film reference="../../../../model.Member[56]/ratedFilms/entry[2]/model.Film"></model.Film><model.Rating>TERRIBLE</model.Rating></entry><entry><model.Film reference="../../../../model.Member[79]/ratedFilms/entry[3]/model.Film"></model.Film><model.Rating>REALLY_LIKED_IT</model.Rating></entry><entry><model.Film reference="../../../../model.Member[74]/ratedFilms/entry[5]/model.Film"></model.Film><model.Rating>REALLY_LIKED_IT</model.Rating></entry></ratedFilms><myFilms><model.Film reference="../../../model.Member[74]/ratedFilms/entry/model.Film"></model.Film><model.Film reference="../../ratedFilms/entry[2]/model.Film"></model.Film><model.Film reference="../../../model.Member[74]/ratedFilms/entry[5]/model.Film"></model.Film><model.Film reference="../../../model.Member[56]/ratedFilms/entry[2]/model.Film"></model.Film><model.Film reference="../../ratedFilms/entry/model.Film"></model.Film><model.Film reference="../../../model.Member[79]/ratedFilms/entry[3]/model.Film"></model.Film></myFilms></model.Member><model.Member><firstName>Megan</firstName><lastName>Hope</lastName><accountName>Megan</accountName><passWord>pass</passWord><ratedFilms><entry><model.Film><id>34</id><title>Ong-bak</title><year>2003</year><genre>Action</genre><ratings><model.Rating>TERRIBLE</model.Rating><model.Rating>REALLY_LIKED_IT</model.Rating></ratings><totalRatingValue>0</totalRatingValue><numOfViewers>2</numOfViewers></model.Film><model.Rating>REALLY_LIKED_IT</model.Rating></entry><entry><model.Film reference="../../../../model.Member[72]/ratedFilms/entry/model.Film"></model.Film><model.Rating>REALLY_LIKED_IT</model.Rating></entry><entry><model.Film><id>1</id><title>Stick It</title><year>2006</year><genre>Comedy</genre><ratings><model.Rating>REALLY_LIKED_IT</model.Rating><model.Rating>LIKED_IT</model.Rating><model.Rating>REALLY_LIKED_IT</model.Rating></ratings><totalRatingValue>13</totalRatingValue><numOfViewers>3</numOfViewers></model.Film><model.Rating>REALLY_LIKED_IT</model.Rating></entry><entry><model.Film><id>33</id><title>Unfaithful</title><year>2002</year><genre>Drama</genre><ratings><model.Rating>LIKED_IT</model.Rating><model.Rating>TERRIBLE</model.Rating></ratings><totalRatingValue>-2</totalRatingValue><numOfViewers>2</numOfViewers></model.Film><model.Rating>TERRIBLE</model.Rating></entry><entry><model.Film><id>40</id><title>Hairspray</title><year>2007</year><genre>Comedy</genre><ratings><model.Rating>TERRIBLE</model.Rating></ratings><totalRatingValue>-5</totalRatingValue><numOfViewers>1</numOfViewers></model.Film><model.Rating>TERRIBLE</model.Rating></entry><entry><model.Film><id>5</id><title>Anything Else</title><year>2003</year><genre>Comedy</genre><ratings><model.Rating>TERRIBLE</model.Rating></ratings><totalRatingValue>-5</totalRatingValue><numOfViewers>1</numOfViewers></model.Film><model.Rating>TERRIBLE</model.Rating></entry><entry><model.Film><id>23</id><title>Outlander</title><year>2008</year><genre>Action</genre><ratings><model.Rating>TERRIBLE</model.Rating></ratings><totalRatingValue>-5</totalRatingValue><numOfViewers>1</numOfViewers></model.Film><model.Rating>TERRIBLE</model.Rating></entry><entry><model.Film><id>55</id><title>Star Trek</title><year>2009</year><genre>Action</genre><ratings><model.Rating>TERRIBLE</model.Rating></ratings><totalRatingValue>-5</totalRatingValue><numOfViewers>1</numOfViewers></model.Film><model.Rating>TERRIBLE</model.Rating></entry><entry><model.Film><id>14</id><title>Femme Fatale</title><year>2002</year><genre>Crime</genre><ratings><model.Rating>TERRIBLE</model.Rating></ratings><totalRatingValue>-5</totalRatingValue><numOfViewers>1</numOfViewers></model.Film><model.Rating>TERRIBLE</model.Rating></entry><entry><model.Film reference="../../../../model.Member[72]/ratedFilms/entry[6]/model.Film"></model.Film><model.Rating>OK</model.Rating></entry><entry><model.Film><id>3</id><title>Virtuosity</title><year>1995</year><genre>Action</genre><ratings><model.Rating>TERRIBLE</model.Rating></ratings><totalRatingValue>-5</totalRatingValue><numOfViewers>1</numOfViewers></model.Film><model.Rating>TERRIBLE</model.Rating></entry><entry><model.Film><id>66</id><title>Guardians of the Galaxy</title><year>2005</year><genre>Crime</genre><ratings><model.Rating>REALLY_LIKED_IT</model.Rating></ratings><totalRatingValue>5</totalRatingValue><numOfViewers>1</numOfViewers></model.Film><model.Rating>REALLY_LIKED_IT</model.Rating></entry></ratedFilms><myFilms><model.Film reference="../../../model.Member[72]/ratedFilms/entry[6]/model.Film"></model.Film><model.Film reference="../../ratedFilms/entry[11]/model.Film"></model.Film><model.Film reference="../../../model.Member[72]/ratedFilms/entry/model.Film"></model.Film><model.Film reference="../../ratedFilms/entry[4]/model.Film"></model.Film><model.Film reference="../../ratedFilms/entry[9]/model.Film"></model.Film><model.Film reference="../../ratedFilms/entry/model.Film"></model.Film><model.Film reference="../../ratedFilms/entry[6]/model.Film"></model.Film><model.Film reference="../../ratedFilms/entry[12]/model.Film"></model.Film><model.Film reference="../../ratedFilms/entry[3]/model.Film"></model.Film><model.Film reference="../../ratedFilms/entry[5]/model.Film"></model.Film><model.Film reference="../../ratedFilms/entry[7]/model.Film"></model.Film><model.Film reference="../../ratedFilms/entry[8]/model.Film"></model.Film></myFilms></model.Member><model.Member><firstName>jose</firstName><lastName>mouriniho</lastName><accountName>jose</accountName><passWord>pass</passWord><ratedFilms><entry><model.Film><id>61</id><title>Interstellar </title><year>2006</year><genre>Comedy</genre><ratings><model.Rating>REALLY_LIKED_IT</model.Rating></ratings><totalRatingValue>5</totalRatingValue><numOfViewers>1</numOfViewers></model.Film><model.Rating>REALLY_LIKED_IT</model.Rating></entry><entry><model.Film><id>64</id><title>The Hunger Games: Mockingjay - Part 1</title><year>2001</year><genre>Action</genre><ratings><model.Rating>REALLY_LIKED_IT</model.Rating></ratings><totalRatingValue>5</totalRatingValue><numOfViewers>1</numOfViewers></model.Film><model.Rating>REALLY_LIKED_IT</model.Rating></entry><entry><model.Film><id>26</id><title>Rome</title><year>2005</year><genre>Action</genre><ratings><model.Rating>REALLY_LIKED_IT</model.Rating></ratings><totalRatingValue>5</totalRatingValue><numOfViewers>1</numOfViewers></model.Film><model.Rating>REALLY_LIKED_IT</model.Rating></entry><entry><model.Film><id>62</id><title>Big Hero 6 </title><year>1993</year><genre>Action</genre><ratings><model.Rating>REALLY_LIKED_IT</model.Rating><model.Rating>LIKED_IT</model.Rating><model.Rating>OK</model.Rating><model.Rating>TERRIBLE</model.Rating><model.Rating>TERRIBLE</model.Rating><model.Rating>REALLY_LIKED_IT</model.Rating></ratings><totalRatingValue>4</totalRatingValue><numOfViewers>6</numOfViewers></model.Film><model.Rating>REALLY_LIKED_IT</model.Rating></entry><entry><model.Film><id>46</id><title>AVP: Alien vs. Predator</title><year>2004</year><genre>Action</genre><ratings><model.Rating>REALLY_LIKED_IT</model.Rating></ratings><totalRatingValue>5</totalRatingValue><numOfViewers>1</numOfViewers></model.Film><model.Rating>REALLY_LIKED_IT</model.Rating></entry><entry><model.Film><id>45</id><title>Jurassic Park III</title><year>2001</year><genre>Action</genre><ratings><model.Rating>DIDNT_LIKE_IT</model.Rating></ratings><totalRatingValue>-3</totalRatingValue><numOfViewers>1</numOfViewers></model.Film><model.Rating>DIDNT_LIKE_IT</model.Rating></entry><entry><model.Film><id>2</id><title>Batman</title><year>1993</year><genre>Action</genre><ratings><model.Rating>LIKED_IT</model.Rating></ratings><totalRatingValue>3</totalRatingValue><numOfViewers>1</numOfViewers></model.Film><model.Rating>LIKED_IT</model.Rating></entry><entry><model.Film><id>35</id><title>The Lookout</title><year>2007</year><genre>Crime</genre><ratings><model.Rating>REALLY_LIKED_IT</model.Rating><model.Rating>REALLY_LIKED_IT</model.Rating><model.Rating>REALLY_LIKED_IT</model.Rating><model.Rating>REALLY_LIKED_IT</model.Rating><model.Rating>REALLY_LIKED_IT</model.Rating></ratings><totalRatingValue>25</totalRatingValue><numOfViewers>5</numOfViewers></model.Film><model.Rating>REALLY_LIKED_IT</model.Rating></entry></ratedFilms><myFilms><model.Film reference="../../ratedFilms/entry[7]/model.Film"></model.Film><model.Film reference="../../ratedFilms/entry[4]/model.Film"></model.Film><model.Film reference="../../ratedFilms/entry[6]/model.Film"></model.Film><model.Film reference="../../ratedFilms/entry[2]/model.Film"></model.Film><model.Film reference="../../ratedFilms/entry[5]/model.Film"></model.Film><model.Film reference="../../ratedFilms/entry[3]/model.Film"></model.Film><model.Film reference="../../ratedFilms/entry/model.Film"></model.Film><model.Film reference="../../ratedFilms/entry[8]/model.Film"></model.Film></myFilms></model.Member><model.Member><firstName>colum</firstName><lastName>foskin</lastName><accountName>colum</accountName><passWord>pass</passWord><ratedFilms></ratedFilms><myFilms></myFilms></model.Member><model.Member><firstName>carol</firstName><lastName>foskin</lastName><accountName>carol</accountName><passWord>pass</passWord><ratedFilms><entry><model.Film><id>53</id><title>Sweeney Todd: The Demon Barber of Fleet Street</title><year>2007</year><genre>Drama</genre><ratings><model.Rating>REALLY_LIKED_IT</model.Rating></ratings><totalRatingValue>5</totalRatingValue><numOfViewers>1</numOfViewers></model.Film><model.Rating>REALLY_LIKED_IT</model.Rating></entry><entry><model.Film><id>74</id><title>Maleficent</title><year>2014</year><genre>Fantasy</genre><ratings><model.Rating>REALLY_LIKED_IT</model.Rating><model.Rating>REALLY_LIKED_IT</model.Rating><model.Rating>REALLY_LIKED_IT</model.Rating><model.Rating>REALLY_LIKED_IT</model.Rating><model.Rating>REALLY_LIKED_IT</model.Rating><model.Rating>DIDNT_LIKE_IT</model.Rating></ratings><totalRatingValue>22</totalRatingValue><numOfViewers>6</numOfViewers></model.Film><model.Rating>DIDNT_LIKE_IT</model.Rating></entry></ratedFilms><myFilms><model.Film reference="../../ratedFilms/entry/model.Film"></model.Film><model.Film reference="../../ratedFilms/entry[2]/model.Film"></model.Film></myFilms></model.Member><model.Member><firstName>jimmy</firstName><lastName>jones</lastName><accountName>jimmyone</accountName><passWord>pass</passWord><ratedFilms></ratedFilms><myFilms></myFilms></model.Member><model.Member><firstName>jeremy</firstName><lastName>clarkson</lastName><accountName>jermey</accountName><passWord>pass</passWord><ratedFilms></ratedFilms><myFilms></myFilms></model.Member><model.Member><firstName>john</firstName><lastName>terry</lastName><accountName>jterry</accountName><passWord>pass</passWord><ratedFilms></ratedFilms><myFilms></myFilms></model.Member></list>
